_origen.pyd
origen/__bin__/__init__.py
origen/__bin__/bin/.keep
origen/__bin__/bin/origen.exe
origen/__init__.py
origen/application.py
origen/attributes.py
origen/blocks/__init__.py
origen/blocks/arm_debug/controller.py
origen/blocks/arm_debug/dp/controller.py
origen/blocks/arm_debug/jtag_dp/controller.py
origen/blocks/arm_debug/mem_ap/controller.py
origen/blocks/memories.py
origen/boot.py
origen/callbacks.py
origen/compiler.py
origen/controller.py
origen/core/commands/__init__.py
origen/core/commands/credentials.py
origen/core/commands/eval.py
origen/core/plugins.py
origen/errors.py
origen/generator/processor.py
origen/generator/tester_api.py
origen/helpers/__init__.py
origen/helpers/doc/__init__.py
origen/helpers/env.py
origen/helpers/num.py
origen/helpers/regressions/__init__.py
origen/helpers/regressions/cli/__init__.py
origen/helpers/regressions/cli/_origen.py
origen/helpers/regressions/cli/command.py
origen/helpers/regressions/cli/help_msg.py
origen/helpers/regressions/cli/origen.py
origen/interface.py
origen/pins.py
origen/producer.py
origen/registers/actions.py
origen/registers/loader.py
origen/services.py
origen/sub_blocks.py
origen/target.py
origen/tester.py
origen/timesets.py
origen/translator.py
origen/translators/__init__.py
origen/translators/ip_xact.py
origen/unit_helpers.py
origen/utility/__init__.py
origen/utility/github.py
origen/utility/mailer.py
origen/utility/publishers/__init__.py
origen/utility/publishers/poetry.py
origen/utility/release_scribe.py
origen/utility/results.py
origen/utility/transaction.py
origen/utility/unit_testers/__init__.py
origen/utility/unit_testers/pytest.py
origen/web/__init__.py
origen/web/origen_sphinx_extension/__init__.py
origen/web/origen_sphinx_extension/misc.py
origen/web/origen_sphinx_extension/shorthand_defs.py
origen/web/origen_sphinx_extension/subprojects.py
origen/web/origen_sphinx_extension/templating.py
origen/web/origen_sphinx_extension/theme/footer.html
origen/web/origen_sphinx_extension/theme/layout.html
origen-2.0.0.dev8.dist-info/entry_points.txt
origen-2.0.0.dev8.dist-info/METADATA
origen-2.0.0.dev8.dist-info/WHEEL
origen-2.0.0.dev8.dist-info/RECORD
