Metadata-Version: 2.1
Name: origen
Version: 2.0.0.dev8
Summary: Semiconductor Developer's Kit
Home-page: https://origen-sdk.org/o2
License: MIT
Author: Origen-SDK
Requires-Python: >=3.7.0,<3.13
Classifier: License :: OSI Approved :: MIT License
Classifier: Programming Language :: Python :: 3
Classifier: Programming Language :: Python :: 3.7
Classifier: Programming Language :: Python :: 3.8
Classifier: Programming Language :: Python :: 3.9
Classifier: Programming Language :: Python :: 3.10
Classifier: Programming Language :: Python :: 3.11
Requires-Dist: Jinja2 (>=3,<4)
Requires-Dist: beautifulsoup4 (==4.8.2)
Requires-Dist: bs4 (==0.0.1)
Requires-Dist: colorama (>=0.4,<0.5)
Requires-Dist: importlib-metadata (>=1.7.0)
Requires-Dist: mako (==1.1.0)
Requires-Dist: origen_autoapi (==2.0.1)
Requires-Dist: origen_metal (>=0.4.1.dev1,<0.5.0)
Requires-Dist: poetry (>=1.1.14,<2.0.0)
Requires-Dist: recommonmark (>=0)
Requires-Dist: sphinx (==3.0.2)
Requires-Dist: sphinxbootstrap4theme (>=0)
Requires-Dist: termcolor (>=1.1.0)
Requires-Dist: yapf (==0.30)
